sunwaysms/__init__.py
sunwaysms/sunwaysms.py
SunwaySMS-0.1.0.dist-info/LICENSE
SunwaySMS-0.1.0.dist-info/METADATA
SunwaySMS-0.1.0.dist-info/WHEEL
SunwaySMS-0.1.0.dist-info/top_level.txt
SunwaySMS-0.1.0.dist-info/RECORD
