Metadata-Version: 2.1
Name: SunwaySMS
Version: 0.1.0
Summary: Sunway sms webservice for python.
Home-page: https://github.com/shadafrough/SunWay-Python
Author: Sunway ICT Center
Author-email: shadafrough@gmail.com
License: UNKNOWN
Platform: UNKNOWN
Classifier: Programming Language :: Python :: 3
Classifier: License :: OSI Approved :: MIT License
Classifier: Operating System :: OS Independent
License-File: LICENSE
Requires-Dist: zeep
